.git/FETCH_HEAD
.git/HEAD
.git/config
.git/description
.git/hooks/applypatch-msg.sample
.git/hooks/commit-msg.sample
.git/hooks/fsmonitor-watchman.sample
.git/hooks/post-update.sample
.git/hooks/pre-applypatch.sample
.git/hooks/pre-commit.sample
.git/hooks/pre-merge-commit.sample
.git/hooks/pre-push.sample
.git/hooks/pre-rebase.sample
.git/hooks/pre-receive.sample
.git/hooks/prepare-commit-msg.sample
.git/hooks/push-to-checkout.sample
.git/hooks/sendemail-validate.sample
.git/hooks/update.sample
.git/index
.git/info/exclude
.git/logs/HEAD
.git/logs/refs/heads/main
.git/logs/refs/remotes/origin/HEAD
.git/logs/refs/remotes/origin/main
.git/objects/pack/pack-81878e44f170cfc7fda66c9304f62615dd1078cd.idx
.git/objects/pack/pack-81878e44f170cfc7fda66c9304f62615dd1078cd.pack
.git/objects/pack/pack-81878e44f170cfc7fda66c9304f62615dd1078cd.rev
.git/refs/heads/main
.git/refs/remotes/origin/HEAD
.git/refs/remotes/origin/main
.git/shallow
.github/workflows/publish-to-pypi.yml
.gitignore
Assets/ExampleInput/music.wav
Assets/ExampleInput/soundeffects.wav
Assets/ExampleInput/speech.wav
Assets/Figure.png
Example.py
FlashSR/AudioSR/AudioSRUnet.py
FlashSR/AudioSR/EncoderDecoder.py
FlashSR/AudioSR/Vocoder.py
FlashSR/AudioSR/args/mel_argument.yaml
FlashSR/AudioSR/args/model_argument.yaml
FlashSR/AudioSR/autoencoder.py
FlashSR/AudioSR/hifigan/LICENSE
FlashSR/AudioSR/hifigan/__init__.py
FlashSR/AudioSR/hifigan/models.py
FlashSR/AudioSR/hifigan/models_v2.py
FlashSR/AudioSR/latent_diffusion/__init__.py
FlashSR/AudioSR/latent_diffusion/modules/attention.py
FlashSR/AudioSR/latent_diffusion/modules/audiomae/AudioMAE.py
FlashSR/AudioSR/latent_diffusion/modules/audiomae/__init__.py
FlashSR/AudioSR/latent_diffusion/modules/audiomae/models_mae.py
FlashSR/AudioSR/latent_diffusion/modules/audiomae/models_vit.py
FlashSR/AudioSR/latent_diffusion/modules/audiomae/util/crop.py
FlashSR/AudioSR/latent_diffusion/modules/audiomae/util/datasets.py
polflashsr-0.0.2.dist-info/METADATA
polflashsr-0.0.2.dist-info/WHEEL
polflashsr-0.0.2.dist-info/RECORD
